xdcget/__init__.py
xdcget/_version.py
xdcget/config.py
xdcget/errors.py
xdcget/main.py
xdcget/storage.py
xdcget-0.3.0.dist-info/LICENSE
xdcget-0.3.0.dist-info/METADATA
xdcget-0.3.0.dist-info/WHEEL
xdcget-0.3.0.dist-info/entry_points.txt
xdcget-0.3.0.dist-info/top_level.txt
xdcget-0.3.0.dist-info/RECORD
