Metadata-Version: 2.1
Name: xdcget
Version: 0.3.0
Summary: experimental tool for collecting latest releases of webxdc apps
License: MPL-2.0
Project-URL: homepage, https://codeberg.org/webxdc/xdcget
Project-URL: issues, https://codeberg.org/webxdc/xdcget/issues
Classifier: Programming Language :: Python :: 3
Classifier: Development Status :: 4 - Beta
Classifier: License :: OSI Approved :: Mozilla Public License 2.0 (MPL 2.0)
Classifier: Operating System :: POSIX
Requires-Python: >=3.9
License-File: LICENSE
Requires-Dist: requests
Requires-Dist: termcolor
Requires-Dist: toml
